snmp/__init__.py
snmp/ber.py
snmp/dispatcher.py
snmp/engine.py
snmp/exception.py
snmp/pdu.py
snmp/smi.py
snmp/types.py
snmp/typing.py
snmp/utils.py
snmp/cffi/openssl/__init__.py
snmp/cffi/openssl/aes.py
snmp/cffi/openssl/des.py
snmp/manager/__init__.py
snmp/manager/v1.py
snmp/manager/v2c.py
snmp/manager/v3.py
snmp/message/__init__.py
snmp/message/v1.py
snmp/message/v2c.py
snmp/message/v3.py
snmp/openssl/aes.cp39-win_amd64.pyd
snmp/openssl/des.cp39-win_amd64.pyd
snmp/security/__init__.py
snmp/security/levels.py
snmp/security/usm/__init__.py
snmp/security/usm/auth.py
snmp/security/usm/priv/__init__.py
snmp/security/usm/priv/aes.py
snmp/security/usm/priv/des.py
snmp/transport/__init__.py
snmp/transport/udp.py
snmp/transport/generic/udp.py
snmp/transport/posix/udp.py
snmp-0.5.0.dist-info/LICENSE
snmp-0.5.0.dist-info/METADATA
snmp-0.5.0.dist-info/WHEEL
snmp-0.5.0.dist-info/top_level.txt
snmp-0.5.0.dist-info/RECORD
