Metadata-Version: 2.1
Name: snmp
Version: 0.5.0
Summary: A user-friendly SNMP library
Home-page: https://github.com/charlestolley/python-snmp
Author: Charles C. D. Tolley
Author-email: charlescdtolley@protonmail.com
License: MIT
Platform: UNKNOWN
Classifier: Development Status :: 4 - Beta
Classifier: Intended Audience :: Developers
Classifier: License :: OSI Approved :: MIT License
Classifier: Natural Language :: English
Classifier: Operating System :: OS Independent
Classifier: Programming Language :: Python :: 3 :: Only
Classifier: Topic :: System :: Networking
Requires-Python: >=3.6
License-File: LICENSE
Requires-Dist: cffi (>=1.0.0)
